fat_macho-0.4.11.dist-info/METADATA
fat_macho-0.4.11.dist-info/WHEEL
fat_macho.libs/libgcc_s-08f7558e.so.1
fat_macho/__init__.py
fat_macho/__init__.pyi
fat_macho/py.typed
fat_macho/fat_macho.abi3.so
fat_macho-0.4.11.dist-info/RECORD
