Metadata-Version: 2.1
Name: fat_macho
Version: 0.4.11
Summary: Mach-O fat binary writer
Keywords: fat,mach,macho
Home-Page: https://github.com/messense/fat-macho-rs
Author: messense <messense@icloud.com>
Author-email: messense <messense@icloud.com>
License: MIT
Project-URL: Source Code, https://github.com/messense/fat-macho-rs.git
